mat2py_matrix_converter/__init__.py
mat2py_matrix_converter/extract_raw_matrix_str.py
mat2py_matrix_converter/general.py
mat2py_matrix_converter/index_converter.py
mat2py_matrix_converter/matrix_wrapper_converter.py
mat2py_matrix_converter/variable_extractor.py
mat2py_matrix_converter-0.1.0.dist-info/licenses/LICENSE
mat2py_matrix_converter-0.1.0.dist-info/METADATA
mat2py_matrix_converter-0.1.0.dist-info/WHEEL
mat2py_matrix_converter-0.1.0.dist-info/top_level.txt
mat2py_matrix_converter-0.1.0.dist-info/RECORD
