Metadata-Version: 2.4
Name: mat2py_matrix_converter
Version: 0.1.0
Summary: A small utility to convert MATLAB-style matrix strings to Python/torch syntax
Home-page: https://github.com/AngelosGuan/mat2py_matrix_converter.git
Author: Angelos Guan
Classifier: Programming Language :: Python :: 3
Classifier: License :: OSI Approved :: MIT License
Requires-Python: >=3.6
License-File: LICENSE
Dynamic: author
Dynamic: classifier
Dynamic: description
Dynamic: description-content-type
Dynamic: home-page
Dynamic: license-file
Dynamic: requires-python
Dynamic: summary
